st_table_select_cell/__init__.py
st_table_select_cell/example.py
st_table_select_cell/frontend/build/asset-manifest.json
st_table_select_cell/frontend/build/index.html
st_table_select_cell/frontend/build/table.css
st_table_select_cell/frontend/build/static/js/main.111dd7ff.js
st_table_select_cell/frontend/build/static/js/main.111dd7ff.js.LICENSE.txt
st_table_select_cell/frontend/build/static/js/main.111dd7ff.js.map
st_table_select_cell/frontend/build/static/js/main.18f3373b.js
st_table_select_cell/frontend/build/static/js/main.18f3373b.js.LICENSE.txt
st_table_select_cell/frontend/build/static/js/main.18f3373b.js.map
st_table_select_cell/frontend/build/static/js/main.8cd7a845.js
st_table_select_cell/frontend/build/static/js/main.8cd7a845.js.LICENSE.txt
st_table_select_cell/frontend/build/static/js/main.8cd7a845.js.map
streamlit_table_select_cell-0.3.4.dist-info/LICENSE
streamlit_table_select_cell-0.3.4.dist-info/METADATA
streamlit_table_select_cell-0.3.4.dist-info/WHEEL
streamlit_table_select_cell-0.3.4.dist-info/top_level.txt
streamlit_table_select_cell-0.3.4.dist-info/RECORD
