Metadata-Version: 2.1
Name: streamlit-table-select-cell
Version: 0.3.4
Summary: Streamlit component that allows you to select|click a cell in a table and get its rowId and columnIndex
Home-page: https://github.com/songjinghe/streamlit-table-select-cell
Author: Jinghe Song
Author-email: sjh.drizzle@foxmail.com
License: UNKNOWN
Platform: UNKNOWN
Requires-Python: >=3.7
Provides-Extra: devel
